etptypes/__init__.py
etptypes/energistics/__init__.py
etptypes/energistics/etp/__init__.py
etptypes/energistics/etp/v12/__init__.py
etptypes/energistics/etp/v12/datatypes/__init__.py
etptypes/energistics/etp/v12/datatypes/any_array.py
etptypes/energistics/etp/v12/datatypes/any_array_type.py
etptypes/energistics/etp/v12/datatypes/any_logical_array_type.py
etptypes/energistics/etp/v12/datatypes/any_sparse_array.py
etptypes/energistics/etp/v12/datatypes/any_subarray.py
etptypes/energistics/etp/v12/datatypes/array_of_boolean.py
etptypes/energistics/etp/v12/datatypes/array_of_bytes.py
etptypes/energistics/etp/v12/datatypes/array_of_double.py
etptypes/energistics/etp/v12/datatypes/array_of_float.py
etptypes/energistics/etp/v12/datatypes/array_of_int.py
etptypes/energistics/etp/v12/datatypes/array_of_long.py
etptypes/energistics/etp/v12/datatypes/array_of_nullable_boolean.py
etptypes/energistics/etp/v12/datatypes/array_of_nullable_int.py
etptypes/energistics/etp/v12/datatypes/array_of_nullable_long.py
etptypes/energistics/etp/v12/datatypes/array_of_string.py
etptypes/energistics/etp/v12/datatypes/attribute_metadata_record.py
etptypes/energistics/etp/v12/datatypes/channel_data/__init__.py
etptypes/energistics/etp/v12/datatypes/channel_data/channel_change_request_info.py
etptypes/energistics/etp/v12/datatypes/channel_data/channel_data_kind.py
etptypes/energistics/etp/v12/datatypes/channel_data/channel_index_kind.py
etptypes/energistics/etp/v12/datatypes/channel_data/channel_metadata_record.py
etptypes/energistics/etp/v12/datatypes/channel_data/channel_range_info.py
etptypes/energistics/etp/v12/datatypes/channel_data/channel_subscribe_info.py
etptypes/energistics/etp/v12/datatypes/channel_data/data_item.py
etptypes/energistics/etp/v12/datatypes/channel_data/frame_channel_metadata_record.py
etptypes/energistics/etp/v12/datatypes/channel_data/frame_point.py
etptypes/energistics/etp/v12/datatypes/channel_data/frame_row.py
etptypes-1.2.0.dist-info/METADATA
etptypes-1.2.0.dist-info/WHEEL
etptypes-1.2.0.dist-info/entry_points.txt
etptypes-1.2.0.dist-info/licenses/LICENSE
etptypes-1.2.0.dist-info/RECORD
