Metadata-Version: 2.4
Name: etptypes
Version: 1.2.0
Summary: ETP python dev kit
License-Expression: Apache-2.0
License-File: LICENSE
Keywords: ETP
Author: Lionel Untereiner
Author-email: lionel.untereiner@geosiris.com
Maintainer: Valentin Gauthier
Maintainer-email: valentin.gauthier@geosiris.com
Requires-Python: >=3.9, <4.0
Classifier: Programming Language :: Python :: 3
Classifier: Programming Language :: Python :: 3.9
Classifier: Programming Language :: Python :: 3.10
Classifier: Programming Language :: Python :: 3.11
Classifier: Programming Language :: Python :: 3.12
Classifier: Programming Language :: Python :: 3.13
Classifier: Programming Language :: Python :: 3.14
Requires-Dist: pydantic (<2.0.0)
Requires-Dist: typingx (>=0.6.0,<0.7.0)
